LICENSE
MANIFEST.in
README.md
setup.py
pyqtt/__init__.py
pyqtt/client.py
pyqtt/storage.py
pyqtt/mqtt/__init__.py
pyqtt/mqtt/connection.py
pyqtt/mqtt/constants.py
pyqtt/mqtt/handler.py
pyqtt/mqtt/package.py
pyqtt/mqtt/property.py
pyqtt/mqtt/protocol.py
pyqtt/mqtt/utils.py
pyqtt_al0olo.egg-info/PKG-INFO
pyqtt_al0olo.egg-info/SOURCES.txt
pyqtt_al0olo.egg-info/dependency_links.txt
pyqtt_al0olo.egg-info/requires.txt
pyqtt_al0olo.egg-info/top_level.txt
pyqtt_al0olo.egg-info/zip-safe