Metadata-Version: 2.1
Name: pyqtt-al0olo
Version: 0.0.2
Summary: Client for MQTT protocol
Home-page: https://github.com/al0olo/pyqtt
Author: Abdullah Farag
Author-email: ali.frg.c@gmail.com
License: MIT
Download-URL: https://github.com/al0olo/pyqtt
Keywords: Pyqtt MQTT client.
Platform: UNKNOWN
Classifier: Intended Audience :: Developers
Classifier: License :: OSI Approved :: MIT License
Classifier: Natural Language :: English
Classifier: Operating System :: OS Independent
Classifier: Programming Language :: Python
Classifier: Topic :: Software Development :: Libraries :: Python Modules
Requires-Python: >=3.5
Provides-Extra: test
License-File: LICENSE
